[ {
  "@id" : "http://bimerr.iot.linkeddata.es/def/information-objects#",
  "@type" : [ "http://www.w3.org/2002/07/owl#Ontology" ],
  "http://purl.org/dc/terms/creator" : [ {
    "@language" : "en",
    "@value" : "Serge Chávez-Feria"
  }, {
    "@value" : "María Poveda-Villalón"
  } ],
  "http://purl.org/dc/terms/license" : [ {
    "@value" : "http://purl.org/NET/rdflicense/cc-by4.0"
  } ],
  "http://purl.org/dc/terms/publisher" : [ {
    "@value" : "http://www.oeg-upm.net/"
  } ],
  "http://purl.org/dc/terms/title" : [ {
    "@value" : "Information Objects Ontology"
  } ],
  "http://www.w3.org/2002/07/owl#versionInfo" : [ {
    "@value" : "0.0.1"
  } ]
}, {
  "@id" : "http://bimerr.iot.linkeddata.es/def/information-objects#InformationObject",
  "@type" : [ "http://www.w3.org/2002/07/owl#Class" ],
  "http://www.w3.org/2000/01/rdf-schema#comment" : [ {
    "@language" : "en",
    "@value" : "Class that represents any type of file."
  } ],
  "http://www.w3.org/2000/01/rdf-schema#label" : [ {
    "@language" : "en",
    "@value" : "Information object"
  } ]
}, {
  "@id" : "http://bimerr.iot.linkeddata.es/def/information-objects#created",
  "@type" : [ "http://www.w3.org/2002/07/owl#DatatypeProperty" ],
  "http://www.w3.org/2000/01/rdf-schema#comment" : [ {
    "@language" : "en",
    "@value" : "Date when the document has been created."
  } ],
  "http://www.w3.org/2000/01/rdf-schema#label" : [ {
    "@language" : "en",
    "@value" : "created"
  } ]
}, {
  "@id" : "http://bimerr.iot.linkeddata.es/def/information-objects#creator",
  "@type" : [ "http://www.w3.org/2002/07/owl#DatatypeProperty" ],
  "http://www.w3.org/2000/01/rdf-schema#comment" : [ {
    "@language" : "en",
    "@value" : "Creator of the file."
  } ],
  "http://www.w3.org/2000/01/rdf-schema#label" : [ {
    "@language" : "en",
    "@value" : "creator"
  } ]
}, {
  "@id" : "http://bimerr.iot.linkeddata.es/def/information-objects#description",
  "@type" : [ "http://www.w3.org/2002/07/owl#DatatypeProperty" ],
  "http://www.w3.org/2000/01/rdf-schema#comment" : [ {
    "@language" : "en",
    "@value" : "A short description of the content of the file."
  } ],
  "http://www.w3.org/2000/01/rdf-schema#label" : [ {
    "@language" : "en",
    "@value" : "description"
  } ]
}, {
  "@id" : "http://bimerr.iot.linkeddata.es/def/information-objects#filename",
  "@type" : [ "http://www.w3.org/2002/07/owl#DatatypeProperty" ],
  "http://www.w3.org/2000/01/rdf-schema#comment" : [ {
    "@language" : "en",
    "@value" : "Filename or path to the location of the file."
  } ],
  "http://www.w3.org/2000/01/rdf-schema#label" : [ {
    "@language" : "en",
    "@value" : "filename"
  } ]
}, {
  "@id" : "http://bimerr.iot.linkeddata.es/def/information-objects#format",
  "@type" : [ "http://www.w3.org/2002/07/owl#DatatypeProperty" ],
  "http://www.w3.org/2000/01/rdf-schema#comment" : [ {
    "@language" : "en",
    "@value" : "Format or extension of the file."
  } ],
  "http://www.w3.org/2000/01/rdf-schema#label" : [ {
    "@language" : "en",
    "@value" : "format"
  } ]
}, {
  "@id" : "http://bimerr.iot.linkeddata.es/def/information-objects#hasDocumentation",
  "@type" : [ "http://www.w3.org/2002/07/owl#ObjectProperty" ],
  "http://www.w3.org/2000/01/rdf-schema#comment" : [ {
    "@language" : "en",
    "@value" : "Relates an entity (Building, Project, Space, etc) with an information object (file) describing an aspect of that entity."
  } ],
  "http://www.w3.org/2000/01/rdf-schema#label" : [ {
    "@language" : "en",
    "@value" : "has documentation"
  } ]
}, {
  "@id" : "http://bimerr.iot.linkeddata.es/def/information-objects#hasGeometryFile",
  "@type" : [ "http://www.w3.org/2002/07/owl#ObjectProperty" ],
  "http://www.w3.org/2000/01/rdf-schema#comment" : [ {
    "@language" : "en",
    "@value" : "Relates the representation of a building topological element with a file describing its geometric information."
  } ],
  "http://www.w3.org/2000/01/rdf-schema#label" : [ {
    "@language" : "en",
    "@value" : "has geometry file"
  } ],
  "http://www.w3.org/2000/01/rdf-schema#subPropertyOf" : [ {
    "@id" : "http://bimerr.iot.linkeddata.es/def/information-objects#hasDocumentation"
  } ]
}, {
  "@id" : "http://bimerr.iot.linkeddata.es/def/information-objects#hasObxmlFile",
  "@type" : [ "http://www.w3.org/2002/07/owl#ObjectProperty" ],
  "http://www.w3.org/2000/01/rdf-schema#comment" : [ {
    "@language" : "en",
    "@value" : "Relates Space entities with obXML files."
  } ],
  "http://www.w3.org/2000/01/rdf-schema#label" : [ {
    "@language" : "en",
    "@value" : "has obxml file"
  } ],
  "http://www.w3.org/2000/01/rdf-schema#subPropertyOf" : [ {
    "@id" : "http://bimerr.iot.linkeddata.es/def/information-objects#hasDocumentation"
  } ]
}, {
  "@id" : "http://bimerr.iot.linkeddata.es/def/information-objects#hasWorkflowPlan",
  "@type" : [ "http://www.w3.org/2002/07/owl#ObjectProperty" ],
  "http://www.w3.org/2000/01/rdf-schema#comment" : [ {
    "@language" : "en",
    "@value" : "Relates a Project entity with a workflow plan file."
  } ],
  "http://www.w3.org/2000/01/rdf-schema#label" : [ {
    "@language" : "en",
    "@value" : "has workflow plan"
  } ],
  "http://www.w3.org/2000/01/rdf-schema#subPropertyOf" : [ {
    "@id" : "http://bimerr.iot.linkeddata.es/def/information-objects#hasDocumentation"
  } ]
}, {
  "@id" : "http://bimerr.iot.linkeddata.es/def/information-objects#identifier",
  "@type" : [ "http://www.w3.org/2002/07/owl#DatatypeProperty" ],
  "http://www.w3.org/2000/01/rdf-schema#comment" : [ {
    "@language" : "en",
    "@value" : "Identifier of the file."
  } ],
  "http://www.w3.org/2000/01/rdf-schema#label" : [ {
    "@language" : "en",
    "@value" : "identifier"
  } ]
}, {
  "@id" : "http://bimerr.iot.linkeddata.es/def/information-objects#isRelatedToFile",
  "@type" : [ "http://www.w3.org/2002/07/owl#ObjectProperty" ],
  "http://www.w3.org/2000/01/rdf-schema#comment" : [ {
    "@language" : "en",
    "@value" : "Indicated a relationship between files."
  } ],
  "http://www.w3.org/2000/01/rdf-schema#label" : [ {
    "@language" : "en",
    "@value" : "is related to file"
  } ]
}, {
  "@id" : "http://bimerr.iot.linkeddata.es/def/information-objects#lastModificationAuthor",
  "@type" : [ "http://www.w3.org/2002/07/owl#DatatypeProperty" ],
  "http://www.w3.org/2000/01/rdf-schema#comment" : [ {
    "@language" : "en",
    "@value" : "The user who last modified the file."
  } ],
  "http://www.w3.org/2000/01/rdf-schema#label" : [ {
    "@language" : "en",
    "@value" : "las modification author"
  } ]
}, {
  "@id" : "http://bimerr.iot.linkeddata.es/def/information-objects#modified",
  "@type" : [ "http://www.w3.org/2002/07/owl#DatatypeProperty" ],
  "http://www.w3.org/2000/01/rdf-schema#comment" : [ {
    "@language" : "en",
    "@value" : "Date when the file was last modified."
  } ],
  "http://www.w3.org/2000/01/rdf-schema#label" : [ {
    "@language" : "en",
    "@value" : "modified"
  } ]
}, {
  "@id" : "http://bimerr.iot.linkeddata.es/def/information-objects#version",
  "@type" : [ "http://www.w3.org/2002/07/owl#DatatypeProperty" ],
  "http://www.w3.org/2000/01/rdf-schema#comment" : [ {
    "@language" : "en",
    "@value" : "Version of the file."
  } ],
  "http://www.w3.org/2000/01/rdf-schema#label" : [ {
    "@language" : "en",
    "@value" : "version"
  } ]
}, {
  "@id" : "http://purl.org/dc/terms/creator",
  "@type" : [ "http://www.w3.org/2002/07/owl#AnnotationProperty" ]
}, {
  "@id" : "http://purl.org/dc/terms/license",
  "@type" : [ "http://www.w3.org/2002/07/owl#AnnotationProperty" ]
}, {
  "@id" : "http://purl.org/dc/terms/publisher",
  "@type" : [ "http://www.w3.org/2002/07/owl#AnnotationProperty" ]
}, {
  "@id" : "http://purl.org/dc/terms/title",
  "@type" : [ "http://www.w3.org/2002/07/owl#AnnotationProperty" ]
} ]